{
  "addresses": [
    {
      "hnrlbls": [
        "1"
      ], 
      "housenumber": "1", 
      "lat": 50.802625143878, 
      "lon": 3.235914691778, 
      "municipality": "Kortrijk", 
      "pcode": "8510", 
      "source": "afgeleidVanGebouw", 
      "street": "Dokter Vannestestraat"
    }, 
    {
      "hnrlbls": [
        "10"
      ], 
      "housenumber": "10", 
      "lat": 50.802194930751, 
      "lon": 3.235736916949, 
      "municipality": "Kortrijk", 
      "pcode": "8510", 
      "source": "afgeleidVanGebouw", 
      "street": "Dokter Vannestestraat"
    }, 
    {
      "hnrlbls": [
        "10A"
      ], 
      "housenumber": "10A", 
      "lat": 50.802019869828, 
      "lon": 3.23591237322, 
      "municipality": "Kortrijk", 
      "pcode": "8510", 
      "source": "afgeleidVanGebouw", 
      "street": "Dokter Vannestestraat"
    }, 
    {
      "hnrlbls": [
        "12"
      ], 
      "housenumber": "12", 
      "lat": 50.80180631438, 
      "lon": 3.236021222114, 
      "municipality": "Kortrijk", 
      "pcode": "8510", 
      "source": "afgeleidVanGebouw", 
      "street": "Dokter Vannestestraat"
    }, 
    {
      "hnrlbls": [
        "14"
      ], 
      "housenumber": "14", 
      "lat": 50.801638641616, 
      "lon": 3.236086687759, 
      "municipality": "Kortrijk", 
      "pcode": "8510", 
      "source": "afgeleidVanGebouw", 
      "street": "Dokter Vannestestraat"
    }, 
    {
      "hnrlbls": [
        "16"
      ], 
      "housenumber": "16", 
      "lat": 50.801473652994, 
      "lon": 3.236104277036, 
      "municipality": "Kortrijk", 
      "pcode": "8510", 
      "source": "afgeleidVanGebouw", 
      "street": "Dokter Vannestestraat"
    }, 
    {
      "hnrlbls": [
        "18"
      ], 
      "housenumber": "18", 
      "lat": 50.801286779683, 
      "lon": 3.236164528915, 
      "municipality": "Kortrijk", 
      "pcode": "8510", 
      "source": "afgeleidVanGebouw", 
      "street": "Dokter Vannestestraat"
    }, 
    {
      "hnrlbls": [
        "1A"
      ], 
      "housenumber": "1A", 
      "lat": 50.802428563541, 
      "lon": 3.234673322754, 
      "municipality": "Kortrijk", 
      "pcode": "8510", 
      "source": "afgeleidVanGebouw", 
      "street": "Dokter Vannestestraat"
    }, 
    {
      "hnrlbls": [
        "2"
      ], 
      "housenumber": "2", 
      "lat": 50.80215387661, 
      "lon": 3.234810465176, 
      "municipality": "Kortrijk", 
      "pcode": "8510", 
      "source": "afgeleidVanGebouw", 
      "street": "Dokter Vannestestraat"
    }, 
    {
      "hnrlbls": [
        "3"
      ], 
      "housenumber": "3", 
      "lat": 50.802438919867, 
      "lon": 3.236079351211, 
      "municipality": "Kortrijk", 
      "pcode": "8510", 
      "source": "afgeleidVanGebouw", 
      "street": "Dokter Vannestestraat"
    }, 
    {
      "hnrlbls": [
        "4"
      ], 
      "housenumber": "4", 
      "lat": 50.802195860518, 
      "lon": 3.234912455614, 
      "municipality": "Kortrijk", 
      "pcode": "8510", 
      "source": "afgeleidVanGebouw", 
      "street": "Dokter Vannestestraat"
    }, 
    {
      "hnrlbls": [
        "4A"
      ], 
      "housenumber": "4A", 
      "lat": 50.802238207918, 
      "lon": 3.235033448823, 
      "municipality": "Kortrijk", 
      "pcode": "8510", 
      "source": "afgeleidVanGebouw", 
      "street": "Dokter Vannestestraat"
    }, 
    {
      "hnrlbls": [
        "4B"
      ], 
      "housenumber": "4B", 
      "lat": 50.802292434017, 
      "lon": 3.2351184035, 
      "municipality": "Kortrijk", 
      "pcode": "8510", 
      "source": "afgeleidVanGebouw", 
      "street": "Dokter Vannestestraat"
    }, 
    {
      "hnrlbls": [
        "5"
      ], 
      "housenumber": "5", 
      "lat": 50.802243983546, 
      "lon": 3.236244928297, 
      "municipality": "Kortrijk", 
      "pcode": "8510", 
      "source": "afgeleidVanGebouw", 
      "street": "Dokter Vannestestraat"
    }, 
    {
      "hnrlbls": [
        "6"
      ], 
      "housenumber": "6", 
      "lat": 50.802303955135, 
      "lon": 3.235249928788, 
      "municipality": "Kortrijk", 
      "pcode": "8510", 
      "source": "afgeleidVanGebouw", 
      "street": "Dokter Vannestestraat"
    }, 
    {
      "hnrlbls": [
        "7"
      ], 
      "housenumber": "7", 
      "lat": 50.802044249321, 
      "lon": 3.236416436283, 
      "municipality": "Kortrijk", 
      "pcode": "8510", 
      "source": "afgeleidVanGebouw", 
      "street": "Dokter Vannestestraat"
    }, 
    {
      "hnrlbls": [
        "8"
      ], 
      "housenumber": "8", 
      "lat": 50.802421054897, 
      "lon": 3.235542495718, 
      "municipality": "Kortrijk", 
      "pcode": "8510", 
      "source": "afgeleidVanGebouw", 
      "street": "Dokter Vannestestraat"
    }
  ]
}