{
  "addresses": [
    {
      "hnrlbls": [
        "1"
      ], 
      "housenumber": "1", 
      "lat": 50.893450364166966, 
      "lon": 3.335118274028272, 
      "municipality": "Wielsbeke", 
      "pcode": "8710", 
      "source": "manueleAanduidingVanGebouw", 
      "street": "Voetweg"
    }, 
    {
      "hnrlbls": [
        "10"
      ], 
      "housenumber": "10", 
      "lat": 50.89317079555401, 
      "lon": 3.333957391579327, 
      "municipality": "Wielsbeke", 
      "pcode": "8710", 
      "source": "manueleAanduidingVanGebouw", 
      "street": "Voetweg"
    }, 
    {
      "hnrlbls": [
        "12"
      ], 
      "housenumber": "12", 
      "lat": 50.893065277756136, 
      "lon": 3.3337156482842656, 
      "municipality": "Wielsbeke", 
      "pcode": "8710", 
      "source": "manueleAanduidingVanGebouw", 
      "street": "Voetweg"
    }, 
    {
      "hnrlbls": [
        "14"
      ], 
      "housenumber": "14", 
      "lat": 50.892920111670975, 
      "lon": 3.333443222982628, 
      "municipality": "Wielsbeke", 
      "pcode": "8710", 
      "source": "manueleAanduidingVanGebouw", 
      "street": "Voetweg"
    }, 
    {
      "hnrlbls": [
        "2"
      ], 
      "housenumber": "2", 
      "lat": 50.89348952110676, 
      "lon": 3.3345110067450396, 
      "municipality": "Wielsbeke", 
      "pcode": "8710", 
      "source": "manueleAanduidingVanGebouw", 
      "street": "Voetweg"
    }, 
    {
      "hnrlbls": [
        "27"
      ], 
      "housenumber": "27", 
      "lat": 50.89272030341882, 
      "lon": 3.3336830195646514, 
      "municipality": "Wielsbeke", 
      "pcode": "8710", 
      "source": "manueleAanduidingVanGebouw", 
      "street": "Voetweg"
    }, 
    {
      "apptnrs": [
        "0.02", 
        "001", 
        "002", 
        "101", 
        "102", 
        "2.02", 
        "201", 
        "202", 
        "301", 
        "302"
      ], 
      "hnrlbls": [
        "7"
      ], 
      "housenumber": "7", 
      "lat": 50.893269447980124, 
      "lon": 3.3346243094633947, 
      "municipality": "Wielsbeke", 
      "pcode": "8710", 
      "source": "manueleAanduidingVanGebouw", 
      "street": "Voetweg"
    }, 
    {
      "hnrlbls": [
        "8"
      ], 
      "housenumber": "8", 
      "lat": 50.89333146028549, 
      "lon": 3.3342135580859824, 
      "municipality": "Wielsbeke", 
      "pcode": "8710", 
      "source": "manueleAanduidingVanGebouw", 
      "street": "Voetweg"
    }, 
    {
      "apptnrs": [
        "0.01", 
        "0.02", 
        "001", 
        "002", 
        "1.01", 
        "1.02", 
        "101", 
        "102", 
        "2.01", 
        "2.02", 
        "201", 
        "202", 
        "3.01", 
        "3.02", 
        "301", 
        "302"
      ], 
      "hnrlbls": [
        "9"
      ], 
      "housenumber": "9", 
      "lat": 50.89312650116574, 
      "lon": 3.3344709509780044, 
      "municipality": "Wielsbeke", 
      "pcode": "8710", 
      "source": "manueleAanduidingVanGebouw", 
      "street": "Voetweg"
    }
  ]
}