{
  "addresses": [
    {
      "hnrlbls": [
        "1"
      ], 
      "housenumber": "1", 
      "lat": 51.03632485165661, 
      "lon": 4.192458292165568, 
      "municipality": "Buggenhout", 
      "pcode": "9255", 
      "source": "afgeleidVanGebouw", 
      "street": "Brielpark"
    }, 
    {
      "hnrlbls": [
        "2"
      ], 
      "housenumber": "2", 
      "lat": 51.03638224931043, 
      "lon": 4.192309519926552, 
      "municipality": "Buggenhout", 
      "pcode": "9255", 
      "source": "afgeleidVanGebouw", 
      "street": "Brielpark"
    }, 
    {
      "hnrlbls": [
        "3"
      ], 
      "housenumber": "3", 
      "lat": 51.036354364093135, 
      "lon": 4.192116015962776, 
      "municipality": "Buggenhout", 
      "pcode": "9255", 
      "source": "afgeleidVanGebouw", 
      "street": "Brielpark"
    }, 
    {
      "hnrlbls": [
        "4"
      ], 
      "housenumber": "4", 
      "lat": 51.03626487615027, 
      "lon": 4.1920242529069105, 
      "municipality": "Buggenhout", 
      "pcode": "9255", 
      "source": "afgeleidVanGebouw", 
      "street": "Brielpark"
    }
  ]
}