{
  "addresses": [
    {
      "hnrlbls": [
        "11"
      ], 
      "housenumber": "11", 
      "lat": 51.10259482453512, 
      "lon": 4.934499322194809, 
      "municipality": "Geel", 
      "pcode": "2440", 
      "source": "afgeleidVanGebouw", 
      "street": "Paddenhoek"
    }, 
    {
      "hnrlbls": [
        "13"
      ], 
      "housenumber": "13", 
      "lat": 51.101983438801234, 
      "lon": 4.932614451399105, 
      "municipality": "Geel", 
      "pcode": "2440", 
      "source": "afgeleidVanGebouw", 
      "street": "Paddenhoek"
    }, 
    {
      "hnrlbls": [
        "1A"
      ], 
      "housenumber": "1A", 
      "lat": 51.102301863800434, 
      "lon": 4.943321911188914, 
      "municipality": "Geel", 
      "pcode": "2440", 
      "source": "afgeleidVanGebouw", 
      "street": "Paddenhoek"
    }, 
    {
      "hnrlbls": [
        "1H"
      ], 
      "housenumber": "1H", 
      "lat": 51.10231871332923, 
      "lon": 4.942668356403191, 
      "municipality": "Geel", 
      "pcode": "2440", 
      "source": "afgeleidVanGebouw", 
      "street": "Paddenhoek"
    }, 
    {
      "hnrlbls": [
        "2A"
      ], 
      "housenumber": "2A", 
      "lat": 51.10193681548033, 
      "lon": 4.943211909954873, 
      "municipality": "Geel", 
      "pcode": "2440", 
      "source": "manueleAanduidingVanGebouw", 
      "street": "Paddenhoek"
    }, 
    {
      "hnrlbls": [
        "3"
      ], 
      "housenumber": "3", 
      "lat": 51.10219381296852, 
      "lon": 4.942104864264029, 
      "municipality": "Geel", 
      "pcode": "2440", 
      "source": "afgeleidVanGebouw", 
      "street": "Paddenhoek"
    }, 
    {
      "hnrlbls": [
        "4"
      ], 
      "housenumber": "4", 
      "lat": 51.101952231833394, 
      "lon": 4.942926125549705, 
      "municipality": "Geel", 
      "pcode": "2440", 
      "source": "afgeleidVanGebouw", 
      "street": "Paddenhoek"
    }, 
    {
      "hnrlbls": [
        "4A"
      ], 
      "housenumber": "4A", 
      "lat": 51.101938150164486, 
      "lon": 4.942679954798315, 
      "municipality": "Geel", 
      "pcode": "2440", 
      "source": "afgeleidVanGebouw", 
      "street": "Paddenhoek"
    }, 
    {
      "hnrlbls": [
        "5"
      ], 
      "housenumber": "5", 
      "lat": 51.10225729685384, 
      "lon": 4.94180496220994, 
      "municipality": "Geel", 
      "pcode": "2440", 
      "source": "afgeleidVanGebouw", 
      "street": "Paddenhoek"
    }, 
    {
      "hnrlbls": [
        "5A"
      ], 
      "housenumber": "5A", 
      "lat": 51.1022904560139, 
      "lon": 4.941548376174758, 
      "municipality": "Geel", 
      "pcode": "2440", 
      "source": "afgeleidVanGebouw", 
      "street": "Paddenhoek"
    }, 
    {
      "hnrlbls": [
        "5C"
      ], 
      "housenumber": "5C", 
      "lat": 51.102383431665174, 
      "lon": 4.941006118286486, 
      "municipality": "Geel", 
      "pcode": "2440", 
      "source": "afgeleidVanGebouw", 
      "street": "Paddenhoek"
    }, 
    {
      "hnrlbls": [
        "6"
      ], 
      "housenumber": "6", 
      "lat": 51.10192776857046, 
      "lon": 4.942430688661105, 
      "municipality": "Geel", 
      "pcode": "2440", 
      "source": "afgeleidVanGebouw", 
      "street": "Paddenhoek"
    }, 
    {
      "hnrlbls": [
        "7"
      ], 
      "housenumber": "7", 
      "lat": 51.10249152829407, 
      "lon": 4.940255592672823, 
      "municipality": "Geel", 
      "pcode": "2440", 
      "source": "afgeleidVanGebouw", 
      "street": "Paddenhoek"
    }, 
    {
      "hnrlbls": [
        "8"
      ], 
      "housenumber": "8", 
      "lat": 51.1019631466687, 
      "lon": 4.941515092436346, 
      "municipality": "Geel", 
      "pcode": "2440", 
      "source": "afgeleidVanGebouw", 
      "street": "Paddenhoek"
    }, 
    {
      "hnrlbls": [
        "9"
      ], 
      "housenumber": "9", 
      "lat": 51.10286713636539, 
      "lon": 4.935165671464012, 
      "municipality": "Geel", 
      "pcode": "2440", 
      "source": "afgeleidVanGebouw", 
      "street": "Paddenhoek"
    }
  ]
}