{
  "addresses": [
    {
      "housenumber": "1", 
      "huisnrlabel": "1-3", 
      "lat": 51.05416881444304, 
      "lon": 3.727269614033809, 
      "message": "", 
      "pcode": "9000", 
      "source": "manueleAanduidingVanPerceel", 
      "street": "Nederpolder"
    }, 
    {
      "housenumber": "10", 
      "huisnrlabel": "8-10", 
      "lat": 51.05367030231511, 
      "lon": 3.7277948023552745, 
      "message": "", 
      "pcode": "9000", 
      "source": "manueleAanduidingVanPerceel", 
      "street": "Nederpolder"
    }, 
    {
      "housenumber": "11", 
      "huisnrlabel": "9-13", 
      "lat": 51.053848798509826, 
      "lon": 3.727913208202853, 
      "message": "", 
      "pcode": "9000", 
      "source": "manueleAanduidingVanPerceel", 
      "street": "Nederpolder"
    }, 
    {
      "housenumber": "12", 
      "huisnrlabel": "12", 
      "lat": 51.05360347218301, 
      "lon": 3.7280091428761013, 
      "message": "", 
      "pcode": "9000", 
      "source": "manueleAanduidingVanPerceel", 
      "street": "Nederpolder"
    }, 
    {
      "housenumber": "13", 
      "huisnrlabel": "9-13", 
      "lat": 51.053848798509826, 
      "lon": 3.727913208202853, 
      "message": "", 
      "pcode": "9000", 
      "source": "manueleAanduidingVanPerceel", 
      "street": "Nederpolder"
    }, 
    {
      "housenumber": "14", 
      "huisnrlabel": "14", 
      "lat": 51.053557891369884, 
      "lon": 3.7281074652891135, 
      "message": "", 
      "pcode": "9000", 
      "source": "manueleAanduidingVanPerceel", 
      "street": "Nederpolder"
    }, 
    {
      "housenumber": "15", 
      "huisnrlabel": "15", 
      "lat": 51.053710748692204, 
      "lon": 3.728111465115302, 
      "message": "", 
      "pcode": "9000", 
      "source": "manueleAanduidingVanPerceel", 
      "street": "Nederpolder"
    }, 
    {
      "housenumber": "16", 
      "huisnrlabel": "16", 
      "lat": 51.05352017279441, 
      "lon": 3.7280992666330928, 
      "message": "", 
      "pcode": "9000", 
      "source": "manueleAanduidingVanPerceel", 
      "street": "Nederpolder"
    }, 
    {
      "housenumber": "17", 
      "huisnrlabel": "17", 
      "lat": 51.053653428000835, 
      "lon": 3.728199892998038, 
      "message": "", 
      "pcode": "9000", 
      "source": "manueleAanduidingVanPerceel", 
      "street": "Nederpolder"
    }, 
    {
      "housenumber": "18", 
      "huisnrlabel": "18-22", 
      "lat": 51.05342157201749, 
      "lon": 3.728346345103338, 
      "message": "", 
      "pcode": "9000", 
      "source": "manueleAanduidingVanPerceel", 
      "street": "Nederpolder"
    }, 
    {
      "housenumber": "19", 
      "huisnrlabel": "19", 
      "lat": 51.05359761884067, 
      "lon": 3.7283018209807626, 
      "message": "", 
      "pcode": "9000", 
      "source": "manueleAanduidingVanPerceel", 
      "street": "Nederpolder"
    }, 
    {
      "housenumber": "2", 
      "huisnrlabel": "2", 
      "lat": 51.0540898040246, 
      "lon": 3.7268608546249817, 
      "message": "", 
      "pcode": "9000", 
      "source": "manueleAanduidingVanPerceel", 
      "street": "Nederpolder"
    }, 
    {
      "housenumber": "20", 
      "huisnrlabel": "18-22", 
      "lat": 51.05342157201749, 
      "lon": 3.728346345103338, 
      "message": "", 
      "pcode": "9000", 
      "source": "manueleAanduidingVanPerceel", 
      "street": "Nederpolder"
    }, 
    {
      "housenumber": "21", 
      "huisnrlabel": "21", 
      "lat": 51.05357486093156, 
      "lon": 3.728378508496785, 
      "message": "", 
      "pcode": "9000", 
      "source": "manueleAanduidingVanPerceel", 
      "street": "Nederpolder"
    }, 
    {
      "housenumber": "22", 
      "huisnrlabel": "18-22", 
      "lat": 51.05342157201749, 
      "lon": 3.728346345103338, 
      "message": "", 
      "pcode": "9000", 
      "source": "manueleAanduidingVanPerceel", 
      "street": "Nederpolder"
    }, 
    {
      "housenumber": "23", 
      "huisnrlabel": "23", 
      "lat": 51.053539718042096, 
      "lon": 3.7284622397938856, 
      "message": "", 
      "pcode": "9000", 
      "source": "manueleAanduidingVanPerceel", 
      "street": "Nederpolder"
    }, 
    {
      "housenumber": "24", 
      "huisnrlabel": "24", 
      "lat": 51.05337584900506, 
      "lon": 3.728453297601076, 
      "message": "", 
      "pcode": "9000", 
      "source": "manueleAanduidingVanPerceel", 
      "street": "Nederpolder"
    }, 
    {
      "housenumber": "25", 
      "huisnrlabel": "25", 
      "lat": 51.05350519718836, 
      "lon": 3.728541341378056, 
      "message": "", 
      "pcode": "9000", 
      "source": "manueleAanduidingVanPerceel", 
      "street": "Nederpolder"
    }, 
    {
      "housenumber": "26", 
      "huisnrlabel": "26", 
      "lat": 51.05328493089072, 
      "lon": 3.728632023320955, 
      "message": "", 
      "pcode": "9000", 
      "source": "manueleAanduidingVanPerceel", 
      "street": "Nederpolder"
    }, 
    {
      "housenumber": "3", 
      "huisnrlabel": "1-3", 
      "lat": 51.05416881444304, 
      "lon": 3.727269614033809, 
      "message": "", 
      "pcode": "9000", 
      "source": "manueleAanduidingVanPerceel", 
      "street": "Nederpolder"
    }, 
    {
      "housenumber": "4", 
      "huisnrlabel": "4", 
      "lat": 51.05400486779982, 
      "lon": 3.7271340521300518, 
      "message": "", 
      "pcode": "9000", 
      "source": "manueleAanduidingVanPerceel", 
      "street": "Nederpolder"
    }, 
    {
      "housenumber": "5", 
      "huisnrlabel": "5", 
      "lat": 51.05403925599461, 
      "lon": 3.7275232401737277, 
      "message": "busnrs on this address: 0002, 0201, 0101, 0001, 0202, 0301, 0102", 
      "pcode": "9000", 
      "source": "manueleAanduidingVanPerceel", 
      "street": "Nederpolder"
    }, 
    {
      "housenumber": "6", 
      "huisnrlabel": "6", 
      "lat": 51.05380727373283, 
      "lon": 3.7275074175298175, 
      "message": "", 
      "pcode": "9000", 
      "source": "manueleAanduidingVanPerceel", 
      "street": "Nederpolder"
    }, 
    {
      "housenumber": "6A", 
      "huisnrlabel": "6A", 
      "lat": 51.05373414312709, 
      "lon": 3.7276623128732194, 
      "message": "", 
      "pcode": "9000", 
      "source": "manueleAanduidingVanPerceel", 
      "street": "Nederpolder"
    }, 
    {
      "housenumber": "7", 
      "huisnrlabel": "7", 
      "lat": 51.05390740145967, 
      "lon": 3.7278060350837476, 
      "message": "", 
      "pcode": "9000", 
      "source": "manueleAanduidingVanPerceel", 
      "street": "Nederpolder"
    }, 
    {
      "housenumber": "8", 
      "huisnrlabel": "8-10", 
      "lat": 51.05367030231511, 
      "lon": 3.7277948023552745, 
      "message": "", 
      "pcode": "9000", 
      "source": "manueleAanduidingVanPerceel", 
      "street": "Nederpolder"
    }, 
    {
      "housenumber": "9", 
      "huisnrlabel": "9-13", 
      "lat": 51.053848798509826, 
      "lon": 3.727913208202853, 
      "message": "", 
      "pcode": "9000", 
      "source": "manueleAanduidingVanPerceel", 
      "street": "Nederpolder"
    }
  ]
}