{
  "addresses": [
    {
      "hnrlbls": [
        "1"
      ], 
      "housenumber": "1", 
      "lat": 51.202617584682635, 
      "lon": 3.9369287376537088, 
      "municipality": "Moerbeke", 
      "pcode": "9180", 
      "source": "afgeleidVanGebouw", 
      "street": "Ooststraat"
    }, 
    {
      "hnrlbls": [
        "10"
      ], 
      "housenumber": "10", 
      "lat": 51.20353324598203, 
      "lon": 3.93858088317519, 
      "municipality": "Moerbeke", 
      "pcode": "9180", 
      "source": "afgeleidVanGebouw", 
      "street": "Ooststraat"
    }, 
    {
      "hnrlbls": [
        "11"
      ], 
      "housenumber": "11", 
      "lat": 51.20274876998956, 
      "lon": 3.937704733094274, 
      "municipality": "Moerbeke", 
      "pcode": "9180", 
      "source": "afgeleidVanGebouw", 
      "street": "Ooststraat"
    }, 
    {
      "hnrlbls": [
        "11A"
      ], 
      "housenumber": "11A", 
      "lat": 51.20299022099189, 
      "lon": 3.9382281823064105, 
      "municipality": "Moerbeke", 
      "pcode": "9180", 
      "source": "afgeleidVanGebouw", 
      "street": "Ooststraat"
    }, 
    {
      "hnrlbls": [
        "12"
      ], 
      "housenumber": "12", 
      "lat": 51.20360735872717, 
      "lon": 3.9388659358161067, 
      "municipality": "Moerbeke", 
      "pcode": "9180", 
      "source": "afgeleidVanGebouw", 
      "street": "Ooststraat"
    }, 
    {
      "hnrlbls": [
        "12A"
      ], 
      "housenumber": "12A", 
      "lat": 51.203865906025904, 
      "lon": 3.939420578669406, 
      "municipality": "Moerbeke", 
      "pcode": "9180", 
      "source": "afgeleidVanGebouw", 
      "street": "Ooststraat"
    }, 
    {
      "hnrlbls": [
        "12B"
      ], 
      "housenumber": "12B", 
      "lat": 51.2037615622762, 
      "lon": 3.9391270735291184, 
      "municipality": "Moerbeke", 
      "pcode": "9180", 
      "source": "afgeleidVanPerceelGrb", 
      "street": "Ooststraat"
    }, 
    {
      "hnrlbls": [
        "13"
      ], 
      "housenumber": "13", 
      "lat": 51.20318946392721, 
      "lon": 3.938614381601373, 
      "municipality": "Moerbeke", 
      "pcode": "9180", 
      "source": "afgeleidVanGebouw", 
      "street": "Ooststraat"
    }, 
    {
      "hnrlbls": [
        "14"
      ], 
      "housenumber": "14", 
      "lat": 51.2038394662165, 
      "lon": 3.9397144276148683, 
      "municipality": "Moerbeke", 
      "pcode": "9180", 
      "source": "afgeleidVanGebouw", 
      "street": "Ooststraat"
    }, 
    {
      "hnrlbls": [
        "15"
      ], 
      "housenumber": "15", 
      "lat": 51.203178452225025, 
      "lon": 3.9388492786033393, 
      "municipality": "Moerbeke", 
      "pcode": "9180", 
      "source": "afgeleidVanGebouw", 
      "street": "Ooststraat"
    }, 
    {
      "hnrlbls": [
        "15A"
      ], 
      "housenumber": "15A", 
      "lat": 51.20335395666186, 
      "lon": 3.9392584502593833, 
      "municipality": "Moerbeke", 
      "pcode": "9180", 
      "source": "afgeleidVanGebouw", 
      "street": "Ooststraat"
    }, 
    {
      "hnrlbls": [
        "16"
      ], 
      "housenumber": "16", 
      "lat": 51.204159608553, 
      "lon": 3.939780167936318, 
      "municipality": "Moerbeke", 
      "pcode": "9180", 
      "source": "afgeleidVanGebouw", 
      "street": "Ooststraat"
    }, 
    {
      "hnrlbls": [
        "16A"
      ], 
      "housenumber": "16A", 
      "lat": 51.20403341898137, 
      "lon": 3.940180100081542, 
      "municipality": "Moerbeke", 
      "pcode": "9180", 
      "source": "afgeleidVanGebouw", 
      "street": "Ooststraat"
    }, 
    {
      "hnrlbls": [
        "17"
      ], 
      "housenumber": "17", 
      "lat": 51.20344311269146, 
      "lon": 3.9396024573779873, 
      "municipality": "Moerbeke", 
      "pcode": "9180", 
      "source": "afgeleidVanGebouw", 
      "street": "Ooststraat"
    }, 
    {
      "hnrlbls": [
        "18-20"
      ], 
      "housenumber": "18", 
      "lat": 51.20435958710691, 
      "lon": 3.940470431146782, 
      "municipality": "Moerbeke", 
      "pcode": "9180", 
      "source": "afgeleidVanGebouw", 
      "street": "Ooststraat"
    }, 
    {
      "hnrlbls": [
        "19"
      ], 
      "housenumber": "19", 
      "lat": 51.20350242614164, 
      "lon": 3.939748142160891, 
      "municipality": "Moerbeke", 
      "pcode": "9180", 
      "source": "afgeleidVanGebouw", 
      "street": "Ooststraat"
    }, 
    {
      "hnrlbls": [
        "2"
      ], 
      "housenumber": "2", 
      "lat": 51.20299598056444, 
      "lon": 3.9369220925168293, 
      "municipality": "Moerbeke", 
      "pcode": "9180", 
      "source": "afgeleidVanGebouw", 
      "street": "Ooststraat"
    }, 
    {
      "hnrlbls": [
        "18-20"
      ], 
      "housenumber": "20", 
      "lat": 51.20435958710691, 
      "lon": 3.940470431146782, 
      "municipality": "Moerbeke", 
      "pcode": "9180", 
      "source": "afgeleidVanGebouw", 
      "street": "Ooststraat"
    }, 
    {
      "hnrlbls": [
        "22"
      ], 
      "housenumber": "22", 
      "lat": 51.20443125328201, 
      "lon": 3.9409751491285765, 
      "municipality": "Moerbeke", 
      "pcode": "9180", 
      "source": "afgeleidVanGebouw", 
      "street": "Ooststraat"
    }, 
    {
      "hnrlbls": [
        "23"
      ], 
      "housenumber": "23", 
      "lat": 51.20364060839954, 
      "lon": 3.9400534985319036, 
      "municipality": "Moerbeke", 
      "pcode": "9180", 
      "source": "afgeleidVanGebouw", 
      "street": "Ooststraat"
    }, 
    {
      "hnrlbls": [
        "23A"
      ], 
      "housenumber": "23A", 
      "lat": 51.20368566985526, 
      "lon": 3.9403345280557485, 
      "municipality": "Moerbeke", 
      "pcode": "9180", 
      "source": "afgeleidVanGebouw", 
      "street": "Ooststraat"
    }, 
    {
      "hnrlbls": [
        "23B"
      ], 
      "housenumber": "23B", 
      "lat": 51.203750028612774, 
      "lon": 3.9405333949794485, 
      "municipality": "Moerbeke", 
      "pcode": "9180", 
      "source": "afgeleidVanGebouw", 
      "street": "Ooststraat"
    }, 
    {
      "hnrlbls": [
        "24"
      ], 
      "housenumber": "24", 
      "lat": 51.20454534886238, 
      "lon": 3.9413070632066325, 
      "municipality": "Moerbeke", 
      "pcode": "9180", 
      "source": "afgeleidVanGebouw", 
      "street": "Ooststraat"
    }, 
    {
      "hnrlbls": [
        "25"
      ], 
      "housenumber": "25", 
      "lat": 51.20400190576455, 
      "lon": 3.9410353120114663, 
      "municipality": "Moerbeke", 
      "pcode": "9180", 
      "source": "afgeleidVanGebouw", 
      "street": "Ooststraat"
    }, 
    {
      "hnrlbls": [
        "26"
      ], 
      "housenumber": "26", 
      "lat": 51.20458870987406, 
      "lon": 3.9417653973650593, 
      "municipality": "Moerbeke", 
      "pcode": "9180", 
      "source": "afgeleidVanGebouw", 
      "street": "Ooststraat"
    }, 
    {
      "hnrlbls": [
        "26A"
      ], 
      "housenumber": "26A", 
      "lat": 51.20469393547364, 
      "lon": 3.9419812101090326, 
      "municipality": "Moerbeke", 
      "pcode": "9180", 
      "source": "afgeleidVanGebouw", 
      "street": "Ooststraat"
    }, 
    {
      "hnrlbls": [
        "27"
      ], 
      "housenumber": "27", 
      "lat": 51.20400361318705, 
      "lon": 3.94110984279174, 
      "municipality": "Moerbeke", 
      "pcode": "9180", 
      "source": "afgeleidVanGebouw", 
      "street": "Ooststraat"
    }, 
    {
      "hnrlbls": [
        "28"
      ], 
      "housenumber": "28", 
      "lat": 51.204738655271775, 
      "lon": 3.9424681510440642, 
      "municipality": "Moerbeke", 
      "pcode": "9180", 
      "source": "afgeleidVanGebouw", 
      "street": "Ooststraat"
    }, 
    {
      "hnrlbls": [
        "28B"
      ], 
      "housenumber": "28B", 
      "lat": 51.204947475307584, 
      "lon": 3.9428969351808356, 
      "municipality": "Moerbeke", 
      "pcode": "9180", 
      "source": "afgeleidVanGebouw", 
      "street": "Ooststraat"
    }, 
    {
      "hnrlbls": [
        "29"
      ], 
      "housenumber": "29", 
      "lat": 51.20403077096469, 
      "lon": 3.9413372399083553, 
      "municipality": "Moerbeke", 
      "pcode": "9180", 
      "source": "afgeleidVanGebouw", 
      "street": "Ooststraat"
    }, 
    {
      "hnrlbls": [
        "31"
      ], 
      "housenumber": "31", 
      "lat": 51.204126843711734, 
      "lon": 3.9415820357099656, 
      "municipality": "Moerbeke", 
      "pcode": "9180", 
      "source": "afgeleidVanGebouw", 
      "street": "Ooststraat"
    }, 
    {
      "hnrlbls": [
        "33"
      ], 
      "housenumber": "33", 
      "lat": 51.20338979843131, 
      "lon": 3.94231047720949, 
      "municipality": "Moerbeke", 
      "pcode": "9180", 
      "source": "afgeleidVanPerceelGrb", 
      "street": "Ooststraat"
    }, 
    {
      "hnrlbls": [
        "35"
      ], 
      "housenumber": "35", 
      "lat": 51.2040550015388, 
      "lon": 3.942049144688856, 
      "municipality": "Moerbeke", 
      "pcode": "9180", 
      "source": "afgeleidVanGebouw", 
      "street": "Ooststraat"
    }, 
    {
      "hnrlbls": [
        "37"
      ], 
      "housenumber": "37", 
      "lat": 51.20450094616436, 
      "lon": 3.9423791749025043, 
      "municipality": "Moerbeke", 
      "pcode": "9180", 
      "source": "afgeleidVanGebouw", 
      "street": "Ooststraat"
    }, 
    {
      "hnrlbls": [
        "39"
      ], 
      "housenumber": "39", 
      "lat": 51.204537226570466, 
      "lon": 3.942794362479759, 
      "municipality": "Moerbeke", 
      "pcode": "9180", 
      "source": "afgeleidVanGebouw", 
      "street": "Ooststraat"
    }, 
    {
      "hnrlbls": [
        "4"
      ], 
      "housenumber": "4", 
      "lat": 51.203351432356335, 
      "lon": 3.93708163373039, 
      "municipality": "Moerbeke", 
      "pcode": "9180", 
      "source": "afgeleidVanGebouw", 
      "street": "Ooststraat"
    }, 
    {
      "hnrlbls": [
        "41"
      ], 
      "housenumber": "41", 
      "lat": 51.20460602990258, 
      "lon": 3.9435558066836807, 
      "municipality": "Moerbeke", 
      "pcode": "9180", 
      "source": "afgeleidVanGebouw", 
      "street": "Ooststraat"
    }, 
    {
      "hnrlbls": [
        "5"
      ], 
      "housenumber": "5", 
      "lat": 51.202665855230514, 
      "lon": 3.9370770939460966, 
      "municipality": "Moerbeke", 
      "pcode": "9180", 
      "source": "afgeleidVanGebouw", 
      "street": "Ooststraat"
    }, 
    {
      "hnrlbls": [
        "6"
      ], 
      "housenumber": "6", 
      "lat": 51.20313050799826, 
      "lon": 3.937579163351087, 
      "municipality": "Moerbeke", 
      "pcode": "9180", 
      "source": "afgeleidVanGebouw", 
      "street": "Ooststraat"
    }, 
    {
      "hnrlbls": [
        "6A"
      ], 
      "housenumber": "6A", 
      "lat": 51.20460026720419, 
      "lon": 3.9381121073067913, 
      "municipality": "Moerbeke", 
      "pcode": "9180", 
      "source": "afgeleidVanGebouw", 
      "street": "Ooststraat"
    }, 
    {
      "hnrlbls": [
        "7"
      ], 
      "housenumber": "7", 
      "lat": 51.202720227023384, 
      "lon": 3.9372471422646815, 
      "municipality": "Moerbeke", 
      "pcode": "9180", 
      "source": "afgeleidVanGebouw", 
      "street": "Ooststraat"
    }, 
    {
      "hnrlbls": [
        "8"
      ], 
      "housenumber": "8", 
      "lat": 51.20342065858996, 
      "lon": 3.9383197943744253, 
      "municipality": "Moerbeke", 
      "pcode": "9180", 
      "source": "afgeleidVanGebouw", 
      "street": "Ooststraat"
    }
  ]
}